Metadata-Version: 2.1
Name: doods
Version: 1.1
Summary: read docs in https://github.com/Kaii-Devv/ds2play
Author: Tamsis X Code
Author-email: ceeskamu@gmail.com
